unduckify/__init__.py
unduckify/reverse.py
unduckify/unduckify.py
unduckify/utils.py
unduckify/library/__init__.py
unduckify/library/maps.py
unduckify/library/mac/__init__.py
unduckify/library/mac/be.json
unduckify/library/mac/bg.json
unduckify/library/mac/ca-fr.json
unduckify/library/mac/ch-de.json
unduckify/library/mac/ch-fr.json
unduckify/library/mac/cz.json
unduckify/library/mac/de.json
unduckify/library/mac/dk.json
unduckify/library/mac/ee.json
unduckify/library/mac/es-la.json
unduckify/library/mac/es.json
unduckify/library/mac/fi.json
unduckify/library/mac/fr.json
unduckify/library/mac/gb.json
unduckify/library/mac/gr.json
unduckify/library/mac/hr.json
unduckify/library/mac/hu.json
unduckify/library/mac/in.json
unduckify/library/mac/is.json
unduckify/library/mac/it.json
unduckify/library/mac/lt.json
unduckify/library/mac/lv.json
unduckify/library/mac/nl.json
unduckify/library/mac/no.json
unduckify/library/mac/pl.json
unduckify/library/mac/pt-br.json
unduckify/library/mac/pt.json
unduckify/library/mac/ro.json
unduckify/library/mac/ru.json
unduckify/library/mac/se.json
unduckify/library/mac/si.json
unduckify/library/mac/sk.json
unduckify/library/mac/tr.json
unduckify/library/mac/ua.json
unduckify/library/mac/us.json
unduckify/library/win/__init__.py
unduckify/library/win/be.json
unduckify/library/win/bg.json
unduckify/library/win/ca-cms.json
unduckify/library/win/ca-fr.json
unduckify/library/win/ch-de.json
unduckify/library/win/ch-fr.json
unduckify/library/win/cz.json
unduckify/library/win/de.json
unduckify/library/win/dk.json
unduckify/library/win/ee.json
unduckify/library/win/es-la.json
unduckify/library/win/es.json
unduckify/library/win/fi.json
unduckify/library/win/fr.json
unduckify/library/win/gb.json
unduckify/library/win/gr.json
unduckify/library/win/hr.json
unduckify/library/win/hu.json
unduckify/library/win/ie.json
unduckify/library/win/in.json
unduckify/library/win/is.json
unduckify/library/win/it.json
unduckify/library/win/lt.json
unduckify-0.1.1.dist-info/LICENSE.txt
unduckify-0.1.1.dist-info/METADATA
unduckify-0.1.1.dist-info/WHEEL
unduckify-0.1.1.dist-info/entry_points.txt
unduckify-0.1.1.dist-info/top_level.txt
unduckify-0.1.1.dist-info/RECORD
