Metadata-Version: 2.1
Name: unduckify
Version: 0.1.1
Summary: Utility to extract duckify payloads from a memory dump.
Author: 0xlibris
License: GNU GENERAL PUBLIC LICENSE
Project-URL: homepage, https://0xlibris.net/posts/reversing_badusb_3/
Project-URL: repository, https://github.com/0xlibris/unduckify
Keywords: reversing,badusb,avr,duckify,unduckify,radare2,r2,r2pipe
License-File: LICENSE.txt
Requires-Dist: r2pipe
